{
    "bauertology": {
        "BRCT_rank": "14"
    },
    "bballnet_quadrants": {
        "quad1_games": [
            {
                "date": "11/15/2025",
                "location": "Neutral",
                "opponent": "Oklahoma",
                "opponent_NET": "48",
                "opponent_rank": null,
                "result": "W",
                "score": "105-99"
            },
            {
                "date": "11/20/2025",
                "location": "Neutral",
                "opponent": "New Mexico",
                "opponent_NET": "46",
                "opponent_rank": null,
                "result": "W",
                "score": "84-72"
            },
            {
                "date": "12/10/2025",
                "location": "Home",
                "opponent": "Wisconsin",
                "opponent_NET": "25",
                "opponent_rank": null,
                "result": "W",
                "score": "90-60"
            },
            {
                "date": "12/13/2025",
                "location": "Away",
                "opponent": "Illinois",
                "opponent_NET": "8",
                "opponent_rank": "13",
                "result": "W",
                "score": "83-80"
            },
            {
                "date": "01/02/2026",
                "location": "Home",
                "opponent": "Michigan St.",
                "opponent_NET": "11",
                "opponent_rank": "9",
                "result": "W",
                "score": "58-56"
            },
            {
                "date": "01/05/2026",
                "location": "Away",
                "opponent": "Ohio St.",
                "opponent_NET": "29",
                "opponent_rank": null,
                "result": "W",
                "score": "72-69"
            },
            {
                "date": "01/10/2026",
                "location": "Away",
                "opponent": "Indiana",
                "opponent_NET": "41",
                "opponent_rank": null,
                "result": "W",
                "score": "83-77"
            },
            {
                "date": "01/17/2026",
                "location": "Away",
                "opponent": "Northwestern",
                "opponent_NET": "65",
                "opponent_rank": null,
                "result": "W",
                "score": "77-58"
            },
            {
                "date": "01/27/2026",
                "location": "Away",
                "opponent": "Michigan",
                "opponent_NET": "2",
                "opponent_rank": "3",
                "result": "L",
                "score": "72-75"
            },
            {
                "date": "02/01/2026",
                "location": "Home",
                "opponent": "Illinois",
                "opponent_NET": "8",
                "opponent_rank": "9",
                "result": "L",
                "score": "69-78"
            },
            {
                "date": "02/10/2026",
                "location": "Home",
                "opponent": "Purdue",
                "opponent_NET": "9",
                "opponent_rank": "13",
                "result": "L",
                "score": "77-80*"
            },
            {
                "date": "02/17/2026",
                "location": "Away",
                "opponent": "Iowa",
                "opponent_NET": "27",
                "opponent_rank": null,
                "result": "L",
                "score": "52-57"
            },
            {
                "date": "03/03/2026",
                "location": "Away",
                "opponent": "UCLA",
                "opponent_NET": "30",
                "opponent_rank": null,
                "result": "L",
                "score": "52-72"
            },
            {
                "date": "03/08/2026",
                "location": "Home",
                "opponent": "Iowa",
                "opponent_NET": "27",
                "opponent_rank": null,
                "result": "W",
                "score": "84-75*"
            },
            {
                "date": "03/13/2026",
                "location": "Neutral",
                "opponent": "Purdue",
                "opponent_NET": "9",
                "opponent_rank": "18",
                "result": "L",
                "score": "58-74"
            }
        ],
        "quad1record": "9-6",
        "quad2_games": [
            {
                "date": "11/21/2025",
                "location": "Neutral",
                "opponent": "Kansas St.",
                "opponent_NET": "100",
                "opponent_rank": null,
                "result": "W",
                "score": "86-85"
            },
            {
                "date": "01/21/2026",
                "location": "Home",
                "opponent": "Washington",
                "opponent_NET": "57",
                "opponent_rank": null,
                "result": "W",
                "score": "76-66"
            },
            {
                "date": "01/24/2026",
                "location": "Away",
                "opponent": "Minnesota",
                "opponent_NET": "81",
                "opponent_rank": null,
                "result": "W",
                "score": "76-57"
            },
            {
                "date": "02/07/2026",
                "location": "Away",
                "opponent": "Rutgers",
                "opponent_NET": "134",
                "opponent_rank": null,
                "result": "W",
                "score": "80-68"
            },
            {
                "date": "02/14/2026",
                "location": "Home",
                "opponent": "Northwestern",
                "opponent_NET": "65",
                "opponent_rank": null,
                "result": "W",
                "score": "68-49"
            },
            {
                "date": "02/28/2026",
                "location": "Away",
                "opponent": "Southern California",
                "opponent_NET": "79",
                "opponent_rank": null,
                "result": "W",
                "score": "82-67"
            }
        ],
        "quad2record": "6-0",
        "quad3_games": [
            {
                "date": "11/25/2025",
                "location": "Home",
                "opponent": "Winthrop",
                "opponent_NET": "131",
                "opponent_rank": null,
                "result": "W",
                "score": "80-73"
            },
            {
                "date": "12/07/2025",
                "location": "Home",
                "opponent": "Creighton",
                "opponent_NET": "83",
                "opponent_rank": null,
                "result": "W",
                "score": "71-50"
            },
            {
                "date": "01/13/2026",
                "location": "Home",
                "opponent": "Oregon",
                "opponent_NET": "109",
                "opponent_rank": null,
                "result": "W",
                "score": "90-55"
            },
            {
                "date": "02/21/2026",
                "location": "Home",
                "opponent": "Penn St.",
                "opponent_NET": "142",
                "opponent_rank": null,
                "result": "W",
                "score": "87-64"
            },
            {
                "date": "02/25/2026",
                "location": "Home",
                "opponent": "Maryland",
                "opponent_NET": "138",
                "opponent_rank": null,
                "result": "W",
                "score": "74-61"
            },
            {
                "date": "03/19/2026",
                "location": "Neutral",
                "opponent": "Troy",
                "opponent_NET": "125",
                "opponent_rank": null,
                "result": "W",
                "score": "76-47"
            }
        ],
        "quad3record": "6-0",
        "quad4_games": [
            {
                "date": "11/03/2025",
                "location": "Home",
                "opponent": "West Ga.",
                "opponent_NET": "298",
                "opponent_rank": null,
                "result": "W",
                "score": "86-53"
            },
            {
                "date": "11/08/2025",
                "location": "Home",
                "opponent": "FIU",
                "opponent_NET": "197",
                "opponent_rank": null,
                "result": "W",
                "score": "96-66"
            },
            {
                "date": "11/11/2025",
                "location": "Home",
                "opponent": "UMES",
                "opponent_NET": "351",
                "opponent_rank": null,
                "result": "W",
                "score": "69-50"
            },
            {
                "date": "11/29/2025",
                "location": "Home",
                "opponent": "USC Upstate",
                "opponent_NET": "303",
                "opponent_rank": null,
                "result": "W",
                "score": "72-63"
            },
            {
                "date": "12/21/2025",
                "location": "Home",
                "opponent": "North Dakota",
                "opponent_NET": "271",
                "opponent_rank": null,
                "result": "W",
                "score": "78-55"
            },
            {
                "date": "12/30/2025",
                "location": "Home",
                "opponent": "New Hampshire",
                "opponent_NET": "348",
                "opponent_rank": null,
                "result": "W",
                "score": "86-55"
            }
        ],
        "quad4record": "6-0"
    },
    "espn": {
        "bpi": 17.0,
        "chance_round_32": "100.0%",
        "chance_sweet_16": "46.8%",
        "non_con_sos": 159.0,
        "proj_tourney_seed": 3.0,
        "proj_win_loss_conf": "15.0-5.0",
        "proj_win_loss_overall": "27.5-6.5",
        "projected_tournament_order": "10",
        "seven_day_change": "",
        "sor": 10.0,
        "sos": 54.0
    },
    "espn_bracketology": {
        "seed": "4"
    },
    "evanmiya": {
        "miya_rating": 18,
        "miya_resume_category": "NA",
        "miya_resume_rank": "NA"
    },
    "haslametrics": {
        "haslam_rating": "12",
        "seed": "3"
    },
    "jthom_analytics": {
        "games": [
            {
                "date": "11/03",
                "kenpom_win_prob": 0.9828739462949616,
                "opponent": "West Georgia",
                "team_win_prob": 0.9934214423683098
            },
            {
                "date": "11/08",
                "kenpom_win_prob": 0.9396576569718392,
                "opponent": "FIU",
                "team_win_prob": 0.9761758054320367
            },
            {
                "date": "11/11",
                "kenpom_win_prob": 0.994010263522081,
                "opponent": "Maryland Eastern Shore",
                "team_win_prob": 0.9977151321769576
            },
            {
                "date": "11/15",
                "kenpom_win_prob": 0.42290820242747,
                "opponent": "Oklahoma",
                "team_win_prob": 0.6670264765882554
            },
            {
                "date": "11/20",
                "kenpom_win_prob": 0.5388126471634401,
                "opponent": "New Mexico",
                "team_win_prob": 0.7615464293733725
            },
            {
                "date": "11/21",
                "kenpom_win_prob": 0.7438844974462233,
                "opponent": "Kansas State",
                "team_win_prob": 0.8881388997333222
            },
            {
                "date": "11/25",
                "kenpom_win_prob": 0.9169994886115652,
                "opponent": "Winthrop",
                "team_win_prob": 0.9667446792734772
            },
            {
                "date": "11/29",
                "kenpom_win_prob": 0.9844592405484486,
                "opponent": "USC Upstate",
                "team_win_prob": 0.9940363187054452
            },
            {
                "date": "12/07",
                "kenpom_win_prob": 0.7514158188135903,
                "opponent": "Creighton",
                "team_win_prob": 0.8883143198020786
            },
            {
                "date": "12/10",
                "kenpom_win_prob": 0.4102415542676449,
                "opponent": "Wisconsin",
                "team_win_prob": 0.6466834704856882
            },
            {
                "date": "12/13",
                "kenpom_win_prob": 0.1066038686482543,
                "opponent": "Illinois",
                "team_win_prob": 0.2389489020610151
            },
            {
                "date": "12/21",
                "kenpom_win_prob": 0.9781909824153776,
                "opponent": "North Dakota",
                "team_win_prob": 0.9915979407568984
            },
            {
                "date": "12/30",
                "kenpom_win_prob": 0.9936559331367552,
                "opponent": "New Hampshire",
                "team_win_prob": 0.9975794342479232
            },
            {
                "date": "01/02",
                "kenpom_win_prob": 0.3127286176291199,
                "opponent": "Michigan State",
                "team_win_prob": 0.5448952702335523
            },
            {
                "date": "01/05",
                "kenpom_win_prob": 0.2301180642015015,
                "opponent": "Ohio State",
                "team_win_prob": 0.4402407194882696
            },
            {
                "date": "01/10",
                "kenpom_win_prob": 0.337715083982562,
                "opponent": "Indiana",
                "team_win_prob": 0.5729668576983885
            },
            {
                "date": "01/13",
                "kenpom_win_prob": 0.8211071672948416,
                "opponent": "Oregon",
                "team_win_prob": 0.9235315137709404
            },
            {
                "date": "01/17",
                "kenpom_win_prob": 0.4659965196337923,
                "opponent": "Northwestern",
                "team_win_prob": 0.6966160671244293
            },
            {
                "date": "01/21",
                "kenpom_win_prob": 0.6472724957113392,
                "opponent": "Washington",
                "team_win_prob": 0.8284285880376707
            },
            {
                "date": "01/24",
                "kenpom_win_prob": 0.5150002796522791,
                "opponent": "Minnesota",
                "team_win_prob": 0.7364267846165767
            },
            {
                "date": "01/27",
                "kenpom_win_prob": 0.066406836805302,
                "opponent": "Michigan",
                "team_win_prob": 0.1576549110311738
            },
            {
                "date": "02/01",
                "kenpom_win_prob": 0.2410813292207263,
                "opponent": "Illinois",
                "team_win_prob": 0.4552945119280676
            },
            {
                "date": "02/07",
                "kenpom_win_prob": 0.7143758347543312,
                "opponent": "Rutgers",
                "team_win_prob": 0.8680918716514757
            },
            {
                "date": "02/10",
                "kenpom_win_prob": 0.2654467392003617,
                "opponent": "Purdue",
                "team_win_prob": 0.4874054682172745
            },
            {
                "date": "02/14",
                "kenpom_win_prob": 0.6990810671527709,
                "opponent": "Northwestern",
                "team_win_prob": 0.8594084365141278
            },
            {
                "date": "02/17",
                "kenpom_win_prob": 0.2398290233062049,
                "opponent": "Iowa",
                "team_win_prob": 0.4535945350284891
            },
            {
                "date": "02/21",
                "kenpom_win_prob": 0.9048773737945002,
                "opponent": "Penn State",
                "team_win_prob": 0.961583416134515
            },
            {
                "date": "02/25",
                "kenpom_win_prob": 0.8588926631134548,
                "opponent": "Maryland",
                "team_win_prob": 0.941231471304193
            },
            {
                "date": "02/28",
                "kenpom_win_prob": 0.5722831549900929,
                "opponent": "USC",
                "team_win_prob": 0.7787905244205553
            },
            {
                "date": "03/03",
                "kenpom_win_prob": 0.2424099957905532,
                "opponent": "UCLA",
                "team_win_prob": 0.4570927048654397
            },
            {
                "date": "03/08",
                "kenpom_win_prob": 0.4564935233494011,
                "opponent": "Iowa",
                "team_win_prob": 0.6884734942608596
            },
            {
                "date": "03/13",
                "kenpom_win_prob": 0.1726628875965244,
                "opponent": "Purdue",
                "team_win_prob": 0.3632563849271435
            }
        ],
        "proj_record": "26.0-6.0",
        "seed": "3"
    },
    "kenpom": {
        "conference_record": "15-5",
        "overall_record": "26-5",
        "rating": 12,
        "record": "28-6",
        "remaining_games": [],
        "sos": 41
    },
    "kpi_sports": {
        "kpi_ranking": 20
    },
    "ncaa": {
        "net_rank": "14"
    },
    "ncaa_wab": {
        "ncaa_wab_rank": 13,
        "ncaa_wab_score": "7.14"
    },
    "next_game": {
        "away_team": "Vanderbilt",
        "away_team_logo": "https://a.espncdn.com/i/teamlogos/ncaa/500/238.png",
        "date_time": "2026-03-22T01:02Z",
        "home_team": "Nebraska",
        "home_team_logo": "https://a.espncdn.com/i/teamlogos/ncaa/500/158.png"
    },
    "polls": {
        "ap_rank": 15,
        "coaches_rank": 14
    },
    "sports_reference": {
        "SRS_rank": 19
    },
    "teamrankings": {
        "make_tournament": "100.0%",
        "most_likely_seed": "4",
        "proj_conf_record": "15.0-5.0",
        "projected_bid_pct": "100%",
        "projected_losses": "6",
        "projected_wins": "26",
        "rank": "19"
    },
    "time": {
        "iso_time": "2026-03-22T01:45:57.220243",
        "time": "Mar. 22 at 1:45 AM"
    },
    "tourney_odds": {
        "seed": "4",
        "status": "Tournament Lock"
    },
    "trank": {
        "torvik_NET": "14",
        "trank": 15,
        "trank_make_tourney": 100.0,
        "trank_proj_record": "27-6 (15-5)",
        "trank_seed": "4",
        "wab_rank": 9,
        "wab_score": "+7.7"
    },
    "warrennolan": {
        "current_conf_record": "15-5",
        "elo": "17",
        "nolan_net": "14",
        "quadrant_1": "10-6",
        "quadrant_2": "6-0",
        "quadrant_3": "6-0",
        "quadrant_4": "6-0",
        "record": "28-6",
        "rpi": "21"
    }
}